when_exactly/__init__.py
when_exactly/api.py
when_exactly/collection.py
when_exactly/custom_collection.py
when_exactly/custom_interval.py
when_exactly/delta.py
when_exactly/interval.py
when_exactly/moment.py
when_exactly-0.0.7.dist-info/WHEEL
when_exactly-0.0.7.dist-info/METADATA
when_exactly-0.0.7.dist-info/RECORD
