Metadata-Version: 2.3
Name: when-exactly
Version: 0.0.7
Summary: Expressive and intuitive date and time library
Author: Nico Bako
Author-email: Nico Bako <>
Classifier: Programming Language :: Python :: 3
Classifier: License :: OSI Approved :: MIT License
Classifier: Operating System :: OS Independent
Requires-Python: >=3.13
Project-URL: Documentation, https://when-exactly.nicobako.me
Project-URL: Homepage, https://github.com/nicobako/when-exactly
Project-URL: Issues, https://github.com/nicobako/when-exactly/issues
